rustdef-0.4.0.dist-info/METADATA
rustdef-0.4.0.dist-info/WHEEL
rustdef-0.4.0.dist-info/license_files/LICENSE
rustdef/magic.py
rustdef/__init__.py
rustdef/rustdef.cpython-38-darwin.so
rustdef-0.4.0.dist-info/RECORD
