Metadata-Version: 2.1
Name: rustdef
Version: 0.4.0
Classifier: Framework :: Jupyter
Classifier: Framework :: IPython
Classifier: Operating System :: MacOS
Classifier: Operating System :: POSIX :: Linux
Classifier: Programming Language :: Python :: 3.7
Classifier: Programming Language :: Python :: 3.8
Classifier: Programming Language :: Python :: 3.9
Classifier: Programming Language :: Python :: 3.10
Classifier: Programming Language :: Python :: 3.11
Classifier: Programming Language :: Rust
Requires-Dist: jupyter
Requires-Dist: pip
Requires-Dist: toml>=0.10
Requires-Dist: maturin>=0.12
License-File: LICENSE
Summary: Jupyter extension which executes Rust functions in Python
Keywords: Jupyter notebook,Rust,Jupyter extension
Author: Ryosuke Kamesawa <emak.ryo@gmail.com>
Author-email: Ryosuke Kamesawa <emak.ryo@gmail.com>
License: MIT
Requires-Python: >=3.7
Project-URL: homepage, https://github.com/emakryo/rustdef
